{
  "錯誤": "System Message",
  "請先登入": "Please log in.",
  "Baccarat": "Baccarat",
  "All": "All",
  "Classic": "Classic",
  "Sports": "Electronic Sports",
  "Slot": "Slot",
  "ChessCard": "ChessCard",
  "熱門": "HOT",
  "最新": "New",
  "Poker": "Poker",
  "Roulette": "Roulette",
  "Erase": "Erase",
  "Fishing": "Fishing",
  "Fish": "Fishing",
  "Electron": "Electronic",
  "Live": "Live",
  "Finance": "Finance",
  "BinaryOption": "Binary Option",
  "目前無資料": "There is no any data yet.",
  "搜尋不到相關遊戲，請重設分類與廠牌": "There is no related games can be found, please re-select the category or game brand.",
  "GameList_All": "All",
  "GameList_Slot": "Slot",
  "GameList_Live": "Live",
  "GameList_Electron": "Electron",
  "GameList_Other": "Other",
  "SlotMaxBetCount3Day": "Maximum slot spins",
  "SlotMaxBetCount30Day": "Lucky Sprite most spins",
  "SlotMaxWinValue7Day": "Maximum draw within 7 days",
  "SlotMaxWinValueYesterday": "The biggest draw the day before yesterday",
  "SlotMaxWinRate7Day": "Maximum rate in 7 days",
  "SlotMaxWinRateYesterday": "The highest rate the day before yesterday",
  "SlotMaxRTPYesterday": "The highest RTP the day before yesterday",
  "全部顯示": "All",
  "品牌": "Brand",
  "遊玩": "Play",
  "超級人氣榜": "Billboard Hot",
  "BTI": "BTI",
  "BG": "BG",
  "BNG": "BNG",
  "CG": "CG",
  "CQ9": "CQ9",
  "EVO": "EVO",
  "KGS": "KGS",
  "KX": "KX",
  "PG": "PG",
  "PNG": "PNG",
  "PP": "PP",
  "VA": "VA",
  "ZEUS": "ZEUS",
  "BBIN": "BBIN",
  "GMW": "GMW",
  "HB": "HB",
  "MG": "MG",
  "NE": "NE",
  "RT": "RT",
  "EWin": "EWin",
  "TH": "TH",
  "WM": "WM",
  "GameList_Brand": "Brand",
  "GameList_Hot": "HOT",
  "GameList_Favo": "Favorites",
  "已加入我的最愛": "Added to Favorites",
  "已移除我的最愛": "Removed From Favorites",
  "本日優選推薦": "Today's Best",
  "進入遊戲": "Play",
  "熱門遊戲": "Best Games",
  "關於我們": "About US",
  "廠牌": "brand"
}